canonicalwebteam/__init__.py
canonicalwebteam/form_generator/__init__.py
canonicalwebteam/form_generator/app.py
canonicalwebteam_form_generator-2.2.0.dist-info/licenses/LICENSE
canonicalwebteam_form_generator-2.2.0.dist-info/METADATA
canonicalwebteam_form_generator-2.2.0.dist-info/WHEEL
canonicalwebteam_form_generator-2.2.0.dist-info/top_level.txt
canonicalwebteam_form_generator-2.2.0.dist-info/RECORD
