Metadata-Version: 2.4
Name: canonicalwebteam.form-generator
Version: 2.2.0
Summary: Python script to generate HTML forms and attach themas a Flask view func.
Home-page: https://github.com/canonical/canonicalwebteam.form-generator
Author: Canonical webteam
Author-email: webteam@canonical.com
License-File: LICENSE
Requires-Dist: Flask
Dynamic: author
Dynamic: author-email
Dynamic: description
Dynamic: description-content-type
Dynamic: home-page
Dynamic: license-file
Dynamic: requires-dist
Dynamic: summary
